nivis_python-0.1.8.dist-info/METADATA
nivis_python-0.1.8.dist-info/WHEEL
nivis_python-0.1.8.dist-info/license_files/COPYING
nivis_python/__init__.py
nivis_python/nivis_python.cp311-win_amd64.pyd
nivis_python-0.1.8.dist-info/RECORD
